README.md
setup.py
f_ck.egg-info/PKG-INFO
f_ck.egg-info/SOURCES.txt
f_ck.egg-info/dependency_links.txt
f_ck.egg-info/requires.txt
f_ck.egg-info/top_level.txt
fuck/ProfanityHandler.py
fuck/__init__.py
fuck/__main__.py
fuck/profane-words.txt
fuck/util/__init__.py
fuck/util/augmentation.py
fuck/util/shape.py
fuck/util/string.py