Metadata-Version: 2.1
Name: f-ck
Version: 0.0.11
Summary: A tiny program for uncensoring russian texts
Home-page: https://github.com/zeionara/fuck
Author: Zeio Nara
Author-email: zeionara@gmail.com
License: Apache 2.0
Project-URL: Documentation, https://github.com/zeionara/fuck#readme
Project-URL: Bug Reports, https://github.com/zeionara/fuck/issues
Project-URL: Source Code, https://github.com/zeionara/fuck
Classifier: Intended Audience :: Developers
Classifier: License :: OSI Approved :: Apache Software License
Classifier: Programming Language :: Python :: 3.11
